test/__init__.py
test/test_group.py
test/test_parse.py
test/test_print.py
test/parsers/__init__.py
test/parsers/test_crosswordle_parser.py
test/parsers/test_diffle_parser.py
test/parsers/test_heardle_parser.py
test/parsers/test_hoordle_parser.py
test/parsers/test_nerdle_parser.py
test/parsers/test_squardle_parser.py
test/parsers/test_vardle_parser.py
test/parsers/test_waffle_parser.py
test/parsers/test_woordle6_parser.py
test/parsers/test_woordle_parser.py
test/parsers/test_wordle_parser.py
test/parsers/test_worldle_parser.py
test/printers/__init__.py
test/printers/test_crosswordle_print.py
test/printers/test_default_print.py
test/printers/test_diffle_print.py
test/printers/test_squardle_print.py
wordleparse/__init__.py
wordleparse/__main__.py
wordleparse/errors.py
wordleparse/gameparser.py
wordleparse/main.py
wordleparse/message.py
wordleparse/parse.py
wordleparse/parser.py
wordleparse/print.py
wordleparse/py.typed
wordleparse/util.py
wordleparse/parsers/__init__.py
wordleparse/parsers/heardle.py
wordleparse/parsers/parsers.py
wordleparse/printers/__init__.py
wordleparse/printers/crosswordle_printer.py
wordleparse/printers/diffle_printer.py
wordleparse/printers/printers.py
wordleparse/printers/squardle_printer.py
wordleparse-1.1.7.dist-info/LICENSE.md
wordleparse-1.1.7.dist-info/METADATA
wordleparse-1.1.7.dist-info/WHEEL
wordleparse-1.1.7.dist-info/entry_points.txt
wordleparse-1.1.7.dist-info/top_level.txt
wordleparse-1.1.7.dist-info/RECORD
