Metadata-Version: 2.1
Name: wordleparse
Version: 1.1.7
Summary: Parse Wordle and Wordle clones from a chat export
Home-page: https://gitlab.com/rensoliemans/wordleparse
Author: Rens Oliemans
Author-email: hello+python@rensoliemans.nl
License: GPLv3
Project-URL: Bug Tracker, https://gitlab.com/RensOliemans/wordleparse/-/issues
Keywords: wordle
Platform: UNKNOWN
Classifier: Development Status :: 5 - Production/Stable
Classifier: Environment :: Console
Classifier: License :: OSI Approved :: GNU General Public License v3 (GPLv3)
Classifier: Operating System :: OS Independent
Classifier: Programming Language :: Python :: 3 :: Only
Classifier: Programming Language :: Python :: 3.7
Classifier: Programming Language :: Python :: 3.8
Classifier: Programming Language :: Python :: 3.9
Classifier: Programming Language :: Python :: 3.10
Classifier: Programming Language :: Python :: 3.11
Requires-Python: >=3.7
License-File: LICENSE.md
Requires-Dist: emoji
